dr_buster/__init__.py
dr_buster/__main__.py
dr_buster/core.py
dr_buster-1.1.0.dist-info/LICENSE
dr_buster-1.1.0.dist-info/METADATA
dr_buster-1.1.0.dist-info/WHEEL
dr_buster-1.1.0.dist-info/top_level.txt
dr_buster-1.1.0.dist-info/RECORD
