Metadata-Version: 2.1
Name: dr-buster
Version: 1.1.0
Summary: Simple, yet effective web path finder implemented with multiprocessing in Python
Home-page: https://github.com/kelj0/dr_buster
Author: kelj0
Author-email: kelj0@protonmail.com
Project-URL: Bug Tracker, https://github.com/kelj0/dr_buster/issues
Classifier: Programming Language :: Python :: 3
Classifier: License :: OSI Approved :: MIT License
Classifier: Operating System :: OS Independent
Requires-Python: >=3
License-File: LICENSE
